{
  "project_info": {
    "project_number": "545233984033",
    "project_id": "subtrack-fb908",
    "storage_bucket": "subtrack-fb908.firebasestorage.app"
  },
  "client": [
    {
      "client_info": {
        "mobilesdk_app_id": "1:545233984033:android:d7dc9478a77a36f4326160",
        "android_client_info": {
          "package_name": "com.subly.app"
        }
      },
      "oauth_client": [],
      "api_key": [
        {
          "current_key": "AIzaSyCnKKtyeiiZuA6Ir31ZXHT4gbgHe6Qb0Po"
        }
      ],
      "services": {
        "appinvite_service": {
          "other_platform_oauth_client": []
        }
      }
    }
  ],
  "configuration_version": "1"
}